marshmallow_fastoneofschema/__init__.py
marshmallow_fastoneofschema/_bootstrap_common.py
marshmallow_fastoneofschema/_hatch_obsoletes.py
marshmallow_fastoneofschema/_pth_bootstrap.py
marshmallow_fastoneofschema/dfm_plugin.py
marshmallow_fastoneofschema/one_of_schema.py
marshmallow_fastoneofschema/py.typed
marshmallow_oneofschema/__init__.py
marshmallow_oneofschema/dfm_plugin.py
marshmallow_oneofschema/one_of_schema.py
marshmallow_oneofschema/py.typed
marshmallow_fastoneofschema.pth
marshmallow_fastoneofschema-2025.9.2.1.dev7.dist-info/METADATA
marshmallow_fastoneofschema-2025.9.2.1.dev7.dist-info/WHEEL
marshmallow_fastoneofschema-2025.9.2.1.dev7.dist-info/entry_points.txt
marshmallow_fastoneofschema-2025.9.2.1.dev7.dist-info/licenses/LICENSE
marshmallow_fastoneofschema-2025.9.2.1.dev7.dist-info/RECORD
