Metadata-Version: 2.4
Name: marshmallow-fastoneofschema
Version: 2025.9.2.1.dev7
Summary: fast marshmallow multiplexing schema
Project-URL: Issues, https://github.com/Kalepa/marshmallow-fastoneofschema/issues
Project-URL: Source, https://github.com/Kalepa/marshmallow-fastoneofschema
Author-email: Maxim Kulkin <maxim.kulkin@gmail.com>, Steven Loria <sloria1@gmail.com>, Maciej Wilczynski <maciej@lupine.software>
Maintainer-email: Maciej Wilczynski <maciej@lupine.software>
License: Copyright 2016-2017 Maxim Kulkin
License-File: LICENSE
Classifier: Intended Audience :: Developers
Classifier: License :: OSI Approved :: MIT License
Classifier: Programming Language :: Python :: 3
Classifier: Programming Language :: Python :: 3.11
Classifier: Programming Language :: Python :: 3.12
Classifier: Programming Language :: Python :: 3.13
Requires-Python: >=3.11
Requires-Dist: marshmallow<5.0.0,>=3.13.0
